lambdarepy/__init__.py
lambdarepy/event.py
lambdarepy/response.py
tests/__init__.py
tests/test_data.py
tests/integration/__init__.py
tests/integration/lambdarepy/__init__.py
tests/integration/lambdarepy/test_event.py
tests/integration/lambdarepy/test_response.py
tests/unit/__init__.py
tests/unit/lambdarepy/__init__.py
tests/unit/lambdarepy/test_event.py
tests/unit/lambdarepy/test_response.py
lambdarepy-1.0.2.dist-info/METADATA
lambdarepy-1.0.2.dist-info/WHEEL
lambdarepy-1.0.2.dist-info/top_level.txt
lambdarepy-1.0.2.dist-info/RECORD
