Metadata-Version: 2.1
Name: lambdarepy
Version: 1.0.2
Summary: lambdarepy description
Author: caolan947 (Caolán Daly)
Author-email: <caolan.day94@gmail.com>
Classifier: Development Status :: 1 - Planning
Classifier: Intended Audience :: Developers
Classifier: Programming Language :: Python :: 3
Classifier: Operating System :: Unix
Classifier: Operating System :: MacOS :: MacOS X
Classifier: Operating System :: Microsoft :: Windows
